youtube_mix_dl/__init__.py
youtube_mix_dl/downloader.py
youtube_mix_dl/utils.py
youtube_mix_dl-0.1.4.dist-info/METADATA
youtube_mix_dl-0.1.4.dist-info/WHEEL
youtube_mix_dl-0.1.4.dist-info/top_level.txt
youtube_mix_dl-0.1.4.dist-info/RECORD
