Metadata-Version: 2.1
Name: youtube_mix_dl
Version: 0.1.4
Summary: A Python library for downloading YouTube Mix playlists
Author-email: Benny-png <mazikuben2@gmail.com>
Project-URL: Homepage, https://github.com/benny-png/youtube_mix_dl
Project-URL: Repository, https://github.com/benny-png/youtube_mix_dl.git
Classifier: Development Status :: 3 - Alpha
Classifier: Intended Audience :: Developers
Classifier: License :: OSI Approved :: MIT License
Classifier: Programming Language :: Python :: 3
Classifier: Programming Language :: Python :: 3.7
Classifier: Programming Language :: Python :: 3.8
Classifier: Programming Language :: Python :: 3.9
Classifier: Programming Language :: Python :: 3.10
Requires-Python: >=3.7
Requires-Dist: selenium>=4.0.0
Requires-Dist: webdriver-manager>=3.8.0
Requires-Dist: yt-dlp>=2023.0.0
